adafruit_circuitpython_pcf8591-1.0.23.dist-info/licenses/LICENSE
adafruit_pcf8591/__init__.py
adafruit_pcf8591/analog_in.py
adafruit_pcf8591/analog_out.py
adafruit_pcf8591/pcf8591.py
adafruit_circuitpython_pcf8591-1.0.23.dist-info/METADATA
adafruit_circuitpython_pcf8591-1.0.23.dist-info/WHEEL
adafruit_circuitpython_pcf8591-1.0.23.dist-info/top_level.txt
adafruit_circuitpython_pcf8591-1.0.23.dist-info/RECORD
